ANNOUNCEMENT.rst
MANIFEST.in
README.rst
distribute_setup.py
setup.py
assertEquals/__init__.py
assertEquals.egg-info/PKG-INFO
assertEquals.egg-info/SOURCES.txt
assertEquals.egg-info/dependency_links.txt
assertEquals.egg-info/entry_points.txt
assertEquals.egg-info/top_level.txt
assertEquals/cli/__init__.py
assertEquals/cli/main.py
assertEquals/cli/reporters.py
assertEquals/cli/utils.py
assertEquals/interactive/__init__.py
assertEquals/interactive/detail.py
assertEquals/interactive/summary.py
assertEquals/interactive/utils.py
assertEquals/interactive/screens/__init__.py
assertEquals/interactive/screens/base.py
assertEquals/interactive/screens/debugging.py
assertEquals/interactive/screens/detail.py
assertEquals/interactive/screens/error.py
assertEquals/interactive/screens/summary.py
assertEquals/tests/__init__.py
assertEquals/tests/cli.py
assertEquals/tests/demo.py
assertEquals/tests/utils.py
assertEquals/tests/interactive/__init__.py
assertEquals/tests/interactive/marshallers.py
assertEquals/tests/interactive/scrollarea.py