Metadata-Version: 1.0
Name: assertEquals
Version: 0.4.3
Summary: assertEquals is an epic testing interface for Python.
Home-page: https://www.github.com/whit537/assertEquals/
Author: Chad Whitacre
Author-email: chad@zetaweb.com
License: UNKNOWN
Platform: UNKNOWN
Classifier: Development Status :: 4 - Beta
Classifier: Environment :: Console
Classifier: Environment :: Console :: Curses
Classifier: Intended Audience :: Developers
Classifier: License :: OSI Approved :: BSD License
Classifier: Natural Language :: English
Classifier: Operating System :: MacOS :: MacOS X
Classifier: Operating System :: Microsoft :: Windows
Classifier: Operating System :: POSIX
Classifier: Programming Language :: Python
Classifier: Topic :: Software Development :: Testing
